{
   "format_version":"1.10.0",
   "minecraft:client_entity":{
      "description":{
         "identifier":"reborn:vaporeon_shiny",
         "materials":{
            "default":"entity_emissive_alpha"
         },
         "textures":{
            "default":"textures/entity/pokemon/shiny/vaporeon_shiny"
         },
         "geometry":{
            "default":"geometry.vaporeon"
         },
         "animations":{
            "look_at_target":"animation.common.look_at_target",
            "chill":"animation.vaporeon.chill",
            "walk":"animation.vaporeon.walk",
            "sit":"animation.vaporeon.sitting",
            "reborn_pokemon_controller":"controller.animation.reborn_pokemon"
         },
         "scripts":{
            "animate":[
               "reborn_pokemon_controller"
            ]
         },
         "render_controllers":[
            "controller.render.reborn_pokemon"
         ]
      }
   }
}