{
    "format_version":"1.12",
    "minecraft:recipe_shapeless":{
        "description":{
            "identifier":"reborn:rattata_shiny_revive"
        },
        "tags":[
            "crafting_table"
        ],
        "ingredients":[
            {
                "item":"reborn:rattata_shiny_fainted"
            },
            {
                "item":"reborn:max_revive"
            }
        ],
        "result":{
            "item":"reborn:rattata_shiny_ball",
            "count":1
        }
    }
}