{
   "format_version":"1.10.0",
   "minecraft:client_entity":{
      "description":{
         "identifier":"reborn:machoke_shiny",
         "materials":{
            "default":"entity_emissive_alpha"
         },
         "textures":{
            "default":"textures/entity/pokemon/shiny/machoke_shiny"
         },
         "geometry":{
            "default":"geometry.machoke"
         },
         "animations":{
            "chill":"animation.machoke.chill",
            "walk":"animation.machoke.walk",
            "sit":"animation.machoke.sitting",
            "reborn_pokemon_controller":"controller.animation.reborn_pokemon"
         },
         "scripts":{
            "animate":[
               "reborn_pokemon_controller"
            ]
         },
         "render_controllers":[
            "controller.render.reborn_pokemon"
         ]
      }
   }
}